{
	"action"   : "create",
	"create"   : "database",
	"teams"    : ["moma"],
	"parent"   : "moma.@{model}",
	"database" : {
		"name"   : "ql",
		"label"  : "Quicklook",
		"desc"   : "MOMA @{desc} quicklook database.",
		"format" : "{TID}",
		"fields" : [
			{
				"name" : "TID",
				"type" : "int(4)",
				"key"  : true
			},
			{
				"name" : "Pressure",
				"type" : "asciitext",
				"meas" : "pressure",
				"unit" : "mTorr",
				"nul"  : true
			},
			{
				"name" : "Current",
				"type" : "asciitext",
				"meas" : "current",
				"unit" : "A",
				"nul"  : true
			},
			{
				"name" : "Chromatogram",
				"type" : "asciitext",
				"unit" : "ions/scan",
				"nul"  : true
			}
		]
	}
}