{
    "action"   : "create",
    "create"   : "database",
    "team"     : "MAVEN",
    "database" : {
        "name"          : "maven_fm_flt_data",
        "label"         : "MAVEN FM Data (Flight)",
        "desc"          : "MAVEN flight model flight science and housekeeping database.",
        "enable_lock"   : false,
        "enable_log"    : false,
        "enable_notify" : false,
        "top_keys"      : 1,
        "fields"        : [
            {
                "name" : "TID",
                "type" : "int(4)",
                "key"  : true
            }
        ],
        "groups": [
            {
                "name"   : "IP",
                "fields" : [
                    {
                        "name" : "t_utc_start",
                        "type" : "int(8)"
                    },
                    {
                        "name" : "t_utc_end",
                        "type" : "int(8)"
                    },
                    {
                        "name" : "t_sclk_start",
                        "type" : "int(8)"
                    },
                    {
                        "name" : "t_sclk_end",
                        "type" : "int(8)"
                    },
                    {
                        "name" : "t_tid_start",
                        "type" : "int(8)"
                    },
                    {
                        "name" : "t_tid_end",
                        "type" : "int(8)"
                    },
                    {
                        "name" : "dt",
                        "type" : "int(8)"
                    },
                    {
                        "name" : "TID",
                        "type" : "int(4)"
                    },
                    {
                        "name" : "Setup Period",
                        "type" : "int(4)"
                    },
                    {
                        "name" : "IP",
                        "type" : "int(4)"
                    },
                    {
                        "name" : "Sample Period",
                        "type" : "int(4)"
                    }
                ]
            },
            {
                "name": "Emission",
                "fields": [
                    {
                        "name" : "t_utc_start",
                        "type" : "int(8)"
                    },
                    {
                        "name" : "t_utc_end",
                        "type" : "int(8)"
                    },
                    {
                        "name" : "t_sclk_start",
                        "type" : "int(8)"
                    },
                    {
                        "name" : "t_sclk_end",
                        "type" : "int(8)"
                    },
                    {
                        "name" : "t_tid_start",
                        "type" : "int(8)"
                    },
                    {
                        "name" : "t_tid_end",
                        "type" : "int(8)"
                    },
                    {
                        "name" : "dt",
                        "type" : "int(8)"
                    },
                    {
                        "name" : "TID",
                        "type" : "int(4)"
                    },
                    {
                        "name" : "Source",
                        "type" : "string(2)"
                    },
                    {
                        "name" : "Filament",
                        "type" : "int(1)"
                    },
                    {
                        "name" : "Emission",
                        "type" : "int(2)",
                        "meas" : "current",
                        "unit" : "microamp"
                    },
                    {
                        "name" : "Em Voltage Raw",
                        "type" : "int(2)",
                        "unit" : "dac"
                    },
                    {
                        "name" : "Em Voltage",
                        "type" : "float(4)",
                        "nul"  : true,
                        "meas" : "voltage",
                        "unit" : "V"
                    }
                ]
            },
            {
                "name": "Science L1",
                "fields": [
                    {
                        "name" : "t_unix",
                        "type" : "int(8)"
                    },
                    {
                        "name" : "t_sclk",
                        "type" : "int(8)"
                    },
                    {
                        "name" : "t_tid",
                        "type" : "int(8)"
                    },
                    {
                        "name" : "tid",
                        "type" : "int(4)"
                    },
                    {
                        "name" : "umkid",
                        "type" : "int(8)"
                    },
                    {
                        "name" : "mass_x100",
                        "type" : "int(4)"
                    },
                    {
                        "name" : "counts",
                        "type" : "int(4)"
                    },
                    {
                        "name" : "cps_raw",
                        "type" : "float(4)"
                    },
                    {
                        "name" : "cps_dt",
                        "type" : "float(4)",
                        "nul"  : true
                    },
                    {
                        "name" : "focus_mode",
                        "type" : "string(8)",
                        "nul"  : true
                    },
                    {
                        "name" : "filament",
                        "type" : "int(1)",
                        "nul"  : true
                    },
                    {
                        "name" : "multiplier",
                        "type" : "int(1)",
                        "nul"  : true
                    },
                    {
                        "name" : "temperature_s",
                        "type" : "float(4)",
                        "meas" : "temperature",
                        "unit" : "C",
                        "nul"  : true
                    },
                    {
                        "name" : "orbit",
                        "type" : "int(4)",
                        "nul"  : true
                    }
                ],
                "indexes" : [
                    ["multiplier", "focus_mode", "mass_x100"],
                    ["multiplier", "focus_mode", "tid", "mass_x100"],
                    ["multiplier", "focus_mode", "umkid", "mass_x100"]
                ]
            },
            {
                "name": "Science L1b",
                "fields": [
                    {
                        "name" : "t_unix",
                        "type" : "int(8)"
                    },
                    {
                        "name" : "t_sclk",
                        "type" : "int(8)"
                    },
                    {
                        "name" : "t_tid",
                        "type" : "int(8)"
                    },
                    {
                        "name" : "tid",
                        "type" : "int(4)"
                    },
                    {
                        "name" : "umkid",
                        "type" : "int(8)"
                    },
                    {
                        "name" : "mass_x100",
                        "type" : "int(4)"
                    },
                    {
                        "name" : "counts",
                        "type" : "int(4)"
                    },
                    {
                        "name" : "cps_raw",
                        "type" : "float(4)"
                    },
                    {
                        "name" : "cps_raw_bkgd",
                        "type" : "float(4)",
                        "nul"  : true
                    },
                    {
                        "name" : "cps_dt",
                        "type" : "float(4)",
                        "nul"  : true
                    },
                    {
                        "name" : "cps_dt_bkgd",
                        "type" : "float(4)",
                        "nul"  : true
                    },
                    {
                        "name" : "bkgd",
                        "type" : "float(4)",
                        "nul"  : true
                    },
                    {
                        "name" : "focus_mode",
                        "type" : "string(8)",
                        "nul"  : true
                    },
                    {
                        "name" : "filament",
                        "type" : "int(1)",
                        "nul"  : true
                    },
                    {
                        "name" : "multiplier",
                        "type" : "int(1)",
                        "nul"  : true
                    },
                    {
                        "name" : "temperature_s",
                        "type" : "float(4)",
                        "meas" : "temperature",
                        "unit" : "C",
                        "nul"  : true
                    },
                    {
                        "name" : "orbit",
                        "type" : "int(4)",
                        "nul"  : true
                    },
                    {
                        "name" : "sol_lat",
                        "type" : "float(4)",
                        "unit" : "deg",
                        "nul"  : true
                    },
                    {
                        "name" : "sol_lon",
                        "type" : "float(4)",
                        "unit" : "deg",
                        "nul"  : true
                    },
                    {
                        "name" : "lst",
                        "type" : "string(32)",
                        "nul"  : true
                    },
                    {
                        "name" : "alt_iau",
                        "type" : "float(4)",
                        "meas" : "altitude",
                        "unit" : "km",
                        "nul"  : true
                    },
                    {
                        "name" : "vsc_iau",
                        "type" : "float(4)",
                        "meas" : "velocity",
                        "unit" : "km/s",
                        "nul"  : true
                    },
                    {
                        "name" : "ram1",
                        "type" : "float(4)",
                        "meas" : "angle",
                        "unit" : "deg",
                        "nul"  : true
                    },
                    {
                        "name" : "ram2_rot_angle",
                        "type" : "float(4)",
                        "meas" : "angle",
                        "unit" : "deg",
                        "nul"  : true
                    },
                    {
                        "name" : "x_iau",
                        "type" : "float(4)",
                        "meas" : "position",
                        "unit" : "km",
                        "nul"  : true
                    },
                    {
                        "name" : "y_iau",
                        "type" : "float(4)",
                        "meas" : "position",
                        "unit" : "km",
                        "nul"  : true
                    },
                    {
                        "name" : "z_iau",
                        "type" : "float(4)",
                        "meas" : "position",
                        "unit" : "km",
                        "nul"  : true
                    },
                    {
                        "name" : "vx_iau",
                        "type" : "float(4)",
                        "meas" : "velocity",
                        "unit" : "km/s",
                        "nul"  : true
                    },
                    {
                        "name" : "vy_iau",
                        "type" : "float(4)",
                        "meas" : "velocity",
                        "unit" : "km/s",
                        "nul"  : true
                    },
                    {
                        "name" : "vz_iau",
                        "type" : "float(4)",
                        "meas" : "velocity",
                        "unit" : "km/s",
                        "nul"  : true
                    },
                    {
                        "name" : "lat",
                        "type" : "float(4)",
                        "unit" : "deg",
                        "nul"  : true
                    },
                    {
                        "name" : "long",
                        "type" : "float(4)",
                        "unit" : "deg",
                        "nul"  : true
                    }
                ],
                "indexes" : [
                    ["multiplier", "focus_mode", "mass_x100", "alt_iau"],
                    ["multiplier", "focus_mode", "tid", "mass_x100"],
                    ["multiplier", "focus_mode", "umkid", "mass_x100"]
                ]
            },
            {
                "name": "Science L1c",
                "fields": [
                    {
                        "name" : "t_unix",
                        "type" : "int(8)"
                    },
                    {
                        "name" : "t_sclk",
                        "type" : "int(8)"
                    },
                    {
                        "name" : "t_tid",
                        "type" : "int(8)"
                    },
                    {
                        "name" : "tid",
                        "type" : "int(4)"
                    },
                    {
                        "name" : "umkid",
                        "type" : "int(8)"
                    },
                    {
                        "name" : "mass_x100",
                        "type" : "int(4)"
                    },
                    {
                        "name" : "counts",
                        "type" : "int(4)"
                    },
                    {
                        "name" : "cps_raw",
                        "type" : "float(4)"
                    },
                    {
                        "name" : "cps_dt",
                        "type" : "float(4)",
                        "nul"  : true
                    },
                    {
                        "name" : "cps_dt_bkgd",
                        "type" : "float(4)",
                        "nul"  : true
                    },
                    {
                        "name" : "focus_mode",
                        "type" : "string(8)",
                        "nul"  : true
                    },
                    {
                        "name" : "filament",
                        "type" : "int(1)",
                        "nul"  : true
                    },
                    {
                        "name" : "multiplier",
                        "type" : "int(1)",
                        "nul"  : true
                    },
                    {
                        "name" : "temperature_s",
                        "type" : "float(4)",
                        "meas" : "temperature",
                        "unit" : "C",
                        "nul"  : true
                    },
                    {
                        "name" : "orbit",
                        "type" : "int(4)",
                        "nul"  : true
                    },
                    {
                        "name" : "alt_iau",
                        "type" : "float(4)",
                        "meas" : "altitude",
                        "unit" : "km",
                        "nul"  : true
                    },
                    {
                        "name" : "vsc_iau",
                        "type" : "float(4)",
                        "meas" : "velocity",
                        "unit" : "km/s",
                        "nul"  : true
                    },
                    {
                        "name" : "ram1",
                        "type" : "float(4)",
                        "meas" : "angle",
                        "unit" : "deg",
                        "nul"  : true
                    },
                    {
                        "name" : "ram2_rot_angle",
                        "type" : "float(4)",
                        "meas" : "angle",
                        "unit" : "deg",
                        "nul"  : true
                    },
                    {
                        "name" : "sol_lat",
                        "type" : "float(4)",
                        "unit" : "deg",
                        "nul"  : true
                    },
                    {
                        "name" : "sol_lon",
                        "type" : "float(4)",
                        "unit" : "deg",
                        "nul"  : true
                    },
                    {
                        "name" : "lst",
                        "type" : "string(32)",
                        "nul"  : true
                    },
                    {
                        "name" : "x_iau",
                        "type" : "float(4)",
                        "meas" : "position",
                        "unit" : "km",
                        "nul"  : true
                    },
                    {
                        "name" : "y_iau",
                        "type" : "float(4)",
                        "meas" : "position",
                        "unit" : "km",
                        "nul"  : true
                    },
                    {
                        "name" : "z_iau",
                        "type" : "float(4)",
                        "meas" : "position",
                        "unit" : "km",
                        "nul"  : true
                    },
                    {
                        "name" : "vx_iau",
                        "type" : "float(4)",
                        "meas" : "velocity",
                        "unit" : "km/s",
                        "nul"  : true
                    },
                    {
                        "name" : "vy_iau",
                        "type" : "float(4)",
                        "meas" : "velocity",
                        "unit" : "km/s",
                        "nul"  : true
                    },
                    {
                        "name" : "vz_iau",
                        "type" : "float(4)",
                        "meas" : "velocity",
                        "unit" : "km/s",
                        "nul"  : true
                    },
                    {
                        "name" : "lat",
                        "type" : "float(4)",
                        "unit" : "deg",
                        "nul"  : true
                    },
                    {
                        "name" : "long",
                        "type" : "float(4)",
                        "unit" : "deg",
                        "nul"  : true
                    }
                ],
                "indexes" : [
                    ["multiplier", "focus_mode", "mass_x100", "alt_iau"],
                    ["multiplier", "focus_mode", "tid", "mass_x100"],
                    ["multiplier", "focus_mode", "umkid", "mass_x100"]
                ]
            },
            {
                "name": "Science L2_csn",
                "fields": [
                    {
                        "name" : "t_unix",
                        "type" : "int(8)"
                    },
                    {
                        "name" : "t_sclk",
                        "type" : "int(8)"
                    },
                    {
                        "name" : "t_tid",
                        "type" : "int(8)"
                    },
                    {
                        "name" : "tid",
                        "type" : "int(4)"
                    },
                    {
                        "name" : "mass_x100",
                        "type" : "int(4)"
                    },
                    {
                        "name" : "cps_dt_bkgd",
                        "type" : "float(4)",
                        "nul"  : true
                    },
                    {
                        "name" : "abundance",
                        "type" : "float(4)",
                        "unit" : "part/cc",
                        "nul"  : true
                    },
                    {
                        "name" : "focus_mode",
                        "type" : "string(8)",
                        "nul"  : true
                    },
                    {
                        "name" : "orbit",
                        "type" : "int(4)",
                        "nul"  : true
                    },
                    {
                        "name" : "alt_iau",
                        "type" : "float(4)",
                        "meas" : "altitude",
                        "unit" : "km",
                        "nul"  : true
                    }
                ],
                "indexes" : [
                    ["mass_x100", "alt_iau"],
                    ["tid", "mass_x100"]
                ]
            },
            {
                "name": "Science L2KP_csn",
                "fields": [
                    {
                        "name" : "t_unix",
                        "type" : "int(8)"
                    },
                    {
                        "name" : "t_sclk",
                        "type" : "int(8)"
                    },
                    {
                        "name" : "t_tid",
                        "type" : "int(8)"
                    },
                    {
                        "name" : "tid",
                        "type" : "int(4)"
                    },
                    {
                        "name" : "mass_x100",
                        "type" : "int(4)"
                    },
                    {
                        "name" : "cps_dt_bkgd",
                        "type" : "float(4)",
                        "nul"  : true
                    },
                    {
                        "name" : "abundance",
                        "type" : "float(4)",
                        "unit" : "part/cc",
                        "nul"  : true
                    },
                    {
                        "name" : "focus_mode",
                        "type" : "string(8)",
                        "nul"  : true
                    },
                    {
                        "name" : "orbit",
                        "type" : "int(4)",
                        "nul"  : true
                    },
                    {
                        "name" : "alt_iau",
                        "type" : "float(4)",
                        "meas" : "altitude",
                        "unit" : "km",
                        "nul"  : true
                    }
                ],
                "indexes" : [
                    ["mass_x100", "alt_iau"],
                    ["tid", "mass_x100"]
                ]
            },
            {
                "name": "Science L2_cso",
                "fields": [
                    {
                        "name" : "t_unix",
                        "type" : "int(8)"
                    },
                    {
                        "name" : "t_sclk",
                        "type" : "int(8)"
                    },
                    {
                        "name" : "t_tid",
                        "type" : "int(8)"
                    },
                    {
                        "name" : "tid",
                        "type" : "int(4)"
                    },
                    {
                        "name" : "mass_x100",
                        "type" : "int(4)"
                    },
                    {
                        "name" : "cps_dt_bkgd",
                        "type" : "float(4)",
                        "nul"  : true
                    },
                    {
                        "name" : "abundance",
                        "type" : "float(4)",
                        "unit" : "part/cc",
                        "nul"  : true
                    },
                    {
                        "name" : "focus_mode",
                        "type" : "string(8)",
                        "nul"  : true
                    },
                    {
                        "name" : "orbit",
                        "type" : "int(4)",
                        "nul"  : true
                    },
                    {
                        "name" : "alt_iau",
                        "type" : "float(4)",
                        "meas" : "altitude",
                        "unit" : "km",
                        "nul"  : true
                    }
                ],
                "indexes" : [
                    ["mass_x100", "alt_iau"],
                    ["tid", "mass_x100"]
                ]
            },
            {
                "name": "Science L2KP_cso",
                "fields": [
                    {
                        "name" : "t_unix",
                        "type" : "int(8)"
                    },
                    {
                        "name" : "t_sclk",
                        "type" : "int(8)"
                    },
                    {
                        "name" : "t_tid",
                        "type" : "int(8)"
                    },
                    {
                        "name" : "tid",
                        "type" : "int(4)"
                    },
                    {
                        "name" : "mass_x100",
                        "type" : "int(4)"
                    },
                    {
                        "name" : "cps_dt_bkgd",
                        "type" : "float(4)",
                        "nul"  : true
                    },
                    {
                        "name" : "abundance",
                        "type" : "float(4)",
                        "unit" : "part/cc",
                        "nul"  : true
                    },
                    {
                        "name" : "focus_mode",
                        "type" : "string(8)",
                        "nul"  : true
                    },
                    {
                        "name" : "orbit",
                        "type" : "int(4)",
                        "nul"  : true
                    },
                    {
                        "name" : "alt_iau",
                        "type" : "float(4)",
                        "meas" : "altitude",
                        "unit" : "km",
                        "nul"  : true
                    }
                ],
                "indexes" : [
                    ["mass_x100", "alt_iau"],
                    ["tid", "mass_x100"]
                ]
            },
            {
                "name": "Science L2_ion",
                "fields": [
                    {
                        "name" : "t_unix",
                        "type" : "int(8)"
                    },
                    {
                        "name" : "t_sclk",
                        "type" : "int(8)"
                    },
                    {
                        "name" : "t_tid",
                        "type" : "int(8)"
                    },
                    {
                        "name" : "tid",
                        "type" : "int(4)"
                    },
                    {
                        "name" : "mass_x100",
                        "type" : "int(4)"
                    },
                    {
                        "name" : "cps_dt",
                        "type" : "float(4)",
                        "nul"  : true
                    },
                    {
                        "name" : "abundance",
                        "type" : "float(4)",
                        "unit" : "part/cc",
                        "nul"  : true
                    },
                    {
                        "name" : "sensitivity",
                        "type" : "float(4)",
                        "nul"  : true
                    },
                    {
                        "name" : "focus_mode",
                        "type" : "string(8)",
                        "nul"  : true
                    },
                    {
                        "name" : "orbit",
                        "type" : "int(4)",
                        "nul"  : true
                    },
                    {
                        "name" : "alt_iau",
                        "type" : "float(4)",
                        "meas" : "altitude",
                        "unit" : "km",
                        "nul"  : true
                    },
                    {
                        "name" : "vsc_iau",
                        "type" : "float(4)",
                        "meas" : "velocity",
                        "unit" : "km/s",
                        "nul"  : true
                    },
                    {
                        "name" : "ram1",
                        "type" : "float(4)",
                        "meas" : "angle",
                        "unit" : "deg",
                        "nul"  : true
                    }
                ],
                "indexes" : [
                    ["mass_x100", "alt_iau"],
                    ["tid", "mass_x100"]
                ]
            },
            {
                "name": "Science L2KP_ion",
                "fields": [
                    {
                        "name" : "t_unix",
                        "type" : "int(8)"
                    },
                    {
                        "name" : "t_sclk",
                        "type" : "int(8)"
                    },
                    {
                        "name" : "t_tid",
                        "type" : "int(8)"
                    },
                    {
                        "name" : "tid",
                        "type" : "int(4)"
                    },
                    {
                        "name" : "mass_x100",
                        "type" : "int(4)"
                    },
                    {
                        "name" : "cps_dt",
                        "type" : "float(4)",
                        "nul"  : true
                    },
                    {
                        "name" : "abundance",
                        "type" : "float(4)",
                        "unit" : "part/cc",
                        "nul"  : true
                    },
                    {
                        "name" : "sensitivity",
                        "type" : "float(4)",
                        "nul"  : true
                    },
                    {
                        "name" : "focus_mode",
                        "type" : "string(8)",
                        "nul"  : true
                    },
                    {
                        "name" : "orbit",
                        "type" : "int(4)",
                        "nul"  : true
                    },
                    {
                        "name" : "alt_iau",
                        "type" : "float(4)",
                        "meas" : "altitude",
                        "unit" : "km",
                        "nul"  : true
                    },
                    {
                        "name" : "vsc_iau",
                        "type" : "float(4)",
                        "meas" : "velocity",
                        "unit" : "km/s",
                        "nul"  : true
                    },
                    {
                        "name" : "ram1",
                        "type" : "float(4)",
                        "meas" : "angle",
                        "unit" : "deg",
                        "nul"  : true
                    }
                ],
                "indexes" : [
                    ["mass_x100", "alt_iau"],
                    ["tid", "mass_x100"]
                ]
            },
            {
                "name"   : "Message",
                "fields" : [
                    {
                        "name"  : "t_utc",
                        "type"  : "int(8)",
                        "index" : true
                    },
                    {
                        "name"  : "t_sclk",
                        "type"  : "int(8)"
                    },
                    {
                        "name"  : "t_tid",
                        "type"  : "int(8)"
                    },
                    {
                        "name"  : "TID",
                        "type"  : "int(4)",
                        "index" : true
                    },
                    {
                        "name"  : "UMKID",
                        "type"  : "int(8)",
                        "index" : true
                    },
                    {
                        "name"  : "UMID",
                        "type"  : "int(8)",
                        "index" : true
                    },
                    {
                        "name"  : "Message",
                        "type"  : "string",
                        "index" : true
                    }
                ]
            },
            {
                "name"        : "Marker",
                "item_format" : "{MK ID} {MK Name}",
                "fields"      : [
                    {
                        "name"  : "t_utc",
                        "type"  : "int(8)",
                        "index" : true
                    },
                    {
                        "name"  : "t_utc_next",
                        "type"  : "int(8)"
                    },
                    {
                        "name"  : "t_sclk",
                        "type"  : "int(8)"
                    },
                    {
                        "name"  : "t_sclk_next",
                        "type"  : "int(8)"
                    },
                    {
                        "name"  : "t_tid",
                        "type"  : "int(8)"
                    },
                    {
                        "name"  : "t_tid_next",
                        "type"  : "int(8)"
                    },
                    {
                        "name"  : "dt",
                        "type"  : "int(8)"
                    },
                    {
                        "name"  : "TID",
                        "type"  : "int(4)",
                        "index" : true
                    },
                    {
                        "name"  : "UMKID",
                        "type"  : "int(8)",
                        "index" : true
                    },
                    {
                        "name"  : "MK ID",
                        "type"  : "int(4)",
                        "index" : true
                    },
                    {
                        "name"  : "MK Name",
                        "type"  : "string(64)",
                        "index" : true,
                        "nul"   : true
                    },
                    {
                        "name"  : "MK Info",
                        "type"  : "string(64)",
                        "index" : true,
                        "nul"   : true
                    }
                ]
            },
            {
                "name"   : "HK",
                "fields" : [
                    {
                        "name" : "t_utc",
                        "type" : "int(8)"
                    },
                    {
                        "name" : "t_tid",
                        "type" : "int(8)"
                    },
                    {
                        "name" : "dt",
                        "type" : "int(8)"
                    },
                    {
                        "name" : "TID",
                        "type" : "int(4)"
                    },
                    {
                        "name" : "UMKID",
                        "type" : "int(8)"
                    },
                    {
                        "name" : "Data ID",
                        "type" : "int(2)"
                    },
                    {
                        "name" : "RAW",
                        "type" : "float(8)"
                    },
                    {
                        "name" : "ENG",
                        "type" : "float(8)"
                    },
                    {
                        "name" : "SCI",
                        "type" : "float(8)"
                    }
                ],
                "indexes" : [
                    ["t_utc", "Data ID"],
                    ["TID"  , "Data ID"],
                    ["UMKID", "Data ID"]
                ]
            },
            {
                "name"   : "HK Bin Time UTC",
                "fields" : [
                    {
                        "name" : "t_utc",
                        "type" : "int(8)"
                    },
                    {
                        "name" : "t_tid",
                        "type" : "int(8)"
                    },
                    {
                        "name" : "TID",
                        "type" : "int(4)"
                    },
                    {
                        "name" : "Data ID",
                        "type" : "int(2)"
                    },
                    {
                        "name" : "Samples",
                        "type" : "int(4)"
                    },
                    {
                        "name" : "RAW Avg",
                        "type" : "float(8)"
                    },
                    {
                        "name" : "RAW Min",
                        "type" : "float(8)"
                    },
                    {
                        "name" : "RAW Max",
                        "type" : "float(8)"
                    },
                    {
                        "name" : "ENG Avg",
                        "type" : "float(8)"
                    },
                    {
                        "name" : "ENG Min",
                        "type" : "float(8)"
                    },
                    {
                        "name" : "ENG Max",
                        "type" : "float(8)"
                    },
                    {
                        "name" : "SCI Avg",
                        "type" : "float(8)"
                    },
                    {
                        "name" : "SCI Min",
                        "type" : "float(8)"
                    },
                    {
                        "name" : "SCI Max",
                        "type" : "float(8)"
                    }
                ],
                "indexes" : [
                    ["t_utc", "Data ID", "Samples"],
                    ["TID"  , "Data ID", "Samples"]
                ]
            },
            {
                "name"   : "HK Bin Time TID",
                "fields" : [
                    {
                        "name" : "t_utc",
                        "type" : "int(8)"
                    },
                    {
                        "name" : "t_tid",
                        "type" : "int(8)"
                    },
                    {
                        "name" : "TID",
                        "type" : "int(4)"
                    },
                    {
                        "name" : "Data ID",
                        "type" : "int(2)"
                    },
                    {
                        "name" : "Samples",
                        "type" : "int(4)"
                    },
                    {
                        "name" : "RAW Avg",
                        "type" : "float(8)"
                    },
                    {
                        "name" : "RAW Min",
                        "type" : "float(8)"
                    },
                    {
                        "name" : "RAW Max",
                        "type" : "float(8)"
                    },
                    {
                        "name" : "ENG Avg",
                        "type" : "float(8)"
                    },
                    {
                        "name" : "ENG Min",
                        "type" : "float(8)"
                    },
                    {
                        "name" : "ENG Max",
                        "type" : "float(8)"
                    },
                    {
                        "name" : "SCI Avg",
                        "type" : "float(8)"
                    },
                    {
                        "name" : "SCI Min",
                        "type" : "float(8)"
                    },
                    {
                        "name" : "SCI Max",
                        "type" : "float(8)"
                    }
                ],
                "indexes" : [
                    ["t_tid", "Data ID", "Samples"],
                    ["TID"  , "Data ID", "Samples"]
                ]
            },
            {
                "name"   : "HK Bin MK",
                "fields" : [
                    {
                        "name" : "t_utc",
                        "type" : "int(8)"
                    },
                    {
                        "name" : "t_tid",
                        "type" : "int(8)"
                    },
                    {
                        "name" : "TID",
                        "type" : "int(4)"
                    },
                    {
                        "name" : "UMKID",
                        "type" : "int(8)"
                    },
                    {
                        "name" : "Data ID",
                        "type" : "int(2)"
                    },
                    {
                        "name" : "Samples",
                        "type" : "int(4)"
                    },
                    {
                        "name" : "RAW Avg",
                        "type" : "float(8)"
                    },
                    {
                        "name" : "RAW Min",
                        "type" : "float(8)"
                    },
                    {
                        "name" : "RAW Max",
                        "type" : "float(8)"
                    },
                    {
                        "name" : "ENG Avg",
                        "type" : "float(8)"
                    },
                    {
                        "name" : "ENG Min",
                        "type" : "float(8)"
                    },
                    {
                        "name" : "ENG Max",
                        "type" : "float(8)"
                    },
                    {
                        "name" : "SCI Avg",
                        "type" : "float(8)"
                    },
                    {
                        "name" : "SCI Min",
                        "type" : "float(8)"
                    },
                    {
                        "name" : "SCI Max",
                        "type" : "float(8)"
                    }
                ],
                "indexes" : [
                    ["t_utc", "Data ID", "Samples"],
                    ["TID"  , "Data ID", "Samples"],
                    ["UMKID", "Data ID", "Samples"]
                ]
            },
            {
                "name"   : "HK Bin TID",
                "fields" : [
                    {
                        "name" : "t_utc",
                        "type" : "int(8)"
                    },
                    {
                        "name" : "TID",
                        "type" : "int(4)"
                    },
                    {
                        "name" : "Data ID",
                        "type" : "int(2)"
                    },
                    {
                        "name" : "Samples",
                        "type" : "int(4)"
                    },
                    {
                        "name" : "RAW Avg",
                        "type" : "float(8)"
                    },
                    {
                        "name" : "RAW Min",
                        "type" : "float(8)"
                    },
                    {
                        "name" : "RAW Max",
                        "type" : "float(8)"
                    },
                    {
                        "name" : "ENG Avg",
                        "type" : "float(8)"
                    },
                    {
                        "name" : "ENG Min",
                        "type" : "float(8)"
                    },
                    {
                        "name" : "ENG Max",
                        "type" : "float(8)"
                    },
                    {
                        "name" : "SCI Avg",
                        "type" : "float(8)"
                    },
                    {
                        "name" : "SCI Min",
                        "type" : "float(8)"
                    },
                    {
                        "name" : "SCI Max",
                        "type" : "float(8)"
                    }
                ],
                "indexes" : [
                    ["t_utc", "Data ID", "Samples"],
                    ["TID"  , "Data ID", "Samples"]
                ]
            }
        ]
    }
}